woocommerce/__init__.py
woocommerce/api.py
woocommerce/oauth.py
WooCommerceMetorik-3.0.0.dist-info/LICENSE.txt
WooCommerceMetorik-3.0.0.dist-info/METADATA
WooCommerceMetorik-3.0.0.dist-info/WHEEL
WooCommerceMetorik-3.0.0.dist-info/top_level.txt
WooCommerceMetorik-3.0.0.dist-info/RECORD
